tests/__init__.py
tests/test_catboost_scorecard.py
tests/test_catboost_wrapper.py
tests/test_cb_constructor.py
tests/test_constructor.py
tests/test_explainer.py
tests/test_interval_scorecard.py
tests/test_parser.py
tests/test_utils.py
tests/test_xgb_constructor.py
tests/test_xgboost_compatibility.py
xbooster/__init__.py
xbooster/_parser.py
xbooster/_utils.py
xbooster/catboost_scorecard.py
xbooster/catboost_wrapper.py
xbooster/cb_constructor.py
xbooster/constructor.py
xbooster/explainer.py
xbooster/xgb_constructor.py
xbooster-0.2.6.post1.dist-info/licenses/LICENSE.md
xbooster-0.2.6.post1.dist-info/METADATA
xbooster-0.2.6.post1.dist-info/WHEEL
xbooster-0.2.6.post1.dist-info/top_level.txt
xbooster-0.2.6.post1.dist-info/RECORD
