Metadata-Version: 2.4
Name: xbooster
Version: 0.2.6.post1
Summary: Explainable Boosted Scoring
Author-email: xRiskLab <contact@xrisklab.ai>
Project-URL: Repository, https://github.com/xRiskLab/xBooster
Project-URL: Homepage, https://github.com/xRiskLab/xBooster
Keywords: machine learning,credit scoring,xgboost,catboost,explainability
Classifier: Development Status :: 4 - Beta
Classifier: Intended Audience :: Developers
Classifier: Intended Audience :: Science/Research
Classifier: License :: OSI Approved :: MIT License
Classifier: Programming Language :: Python :: 3
Classifier: Programming Language :: Python :: 3.10
Classifier: Programming Language :: Python :: 3.11
Classifier: Topic :: Scientific/Engineering :: Artificial Intelligence
Requires-Python: <3.11,>=3.10
License-File: LICENSE.md
Requires-Dist: matplotlib<4.0.0,>=3.8.0
Requires-Dist: numpy<2.0.0,>=1.19.5
Requires-Dist: pandas<3.0.0,>=2.2.2
Requires-Dist: scipy<2.0.0,>=1.11.4
Requires-Dist: scikit-learn<2.0.0,>=1.3.0
Requires-Dist: shap<1.0.0,>=0.44.0
Requires-Dist: catboost<2.0.0,>=1.2.7
Requires-Dist: xgboost<4.0.0,>=2.0.0
Requires-Dist: pyarrow<20.0.0,>=19.0.1
Dynamic: license-file
